setup.py
Deep_ACSA/__init__.py
Deep_ACSA/__main__.py
Deep_ACSA/deep_acsa_gui.py
Deep_ACSA/gui_helpers/__init__.py
Deep_ACSA/gui_helpers/apo_model.py
Deep_ACSA/gui_helpers/calculate_muscle_volume.py
Deep_ACSA/gui_helpers/calibrate.py
Deep_ACSA/gui_helpers/create_manual_masks.py
Deep_ACSA/gui_helpers/data_augmentation.py
Deep_ACSA/gui_helpers/echo_int.py
Deep_ACSA/gui_helpers/file_analysis.py
Deep_ACSA/gui_helpers/model_training.py
Deep_ACSA/gui_helpers/predict_muscle_area.py
docs/source/conf.py
deepacsa-0.3.1.dist-info/METADATA
deepacsa-0.3.1.dist-info/WHEEL
deepacsa-0.3.1.dist-info/licenses/LICENSE
deepacsa-0.3.1.dist-info/RECORD
