Metadata-Version: 2.1
Name: DeepACSA
Version: 0.3.1
Summary: Automatic analysis of transversal muscle ultrasonography images
Project-URL: Homepage, https://github.com/PaulRitsche/DeepACSA
Project-URL: Bug Tracker, https://github.com/PaulRitsche/DeepACSA/issues
Author-email: Paul Ritsche <paul.ritsche@unibas.ch>
License-File: LICENSE
Classifier: Intended Audience :: Science/Research
Classifier: License :: OSI Approved :: Apache Software License
Classifier: Operating System :: Microsoft :: Windows
Classifier: Programming Language :: Python :: 3.9
Requires-Python: >=3.9
Requires-Dist: h5py==3.4.0
Requires-Dist: keras==2.9.0
Requires-Dist: matplotlib==3.5.2
Requires-Dist: numpy==1.21.2
Requires-Dist: opencv-contrib-python==4.5.3.56
Requires-Dist: openpyxl==3.0.9
Requires-Dist: pandas==1.3.3
Requires-Dist: pillow==8.3.2
Requires-Dist: scikit-image==0.18.3
Requires-Dist: scikit-learn==0.24.2
Requires-Dist: tensorflow==2.9.0
Requires-Dist: tqdm==4.62.2
